pyssed/__init__.py
pyssed/bandit.py
pyssed/mad.py
pyssed/model.py
pyssed/py.typed
pyssed/utils.py
pyssed-0.2.0.dist-info/METADATA
pyssed-0.2.0.dist-info/WHEEL
pyssed-0.2.0.dist-info/RECORD
