Metadata-Version: 2.4
Name: pyssed
Version: 0.2.0
Summary: The Mixture Adaptive Design (MAD) and extensions: Robust and precise anytime-valid causal inference in adaptive experiments
Author-email: Daniel Molitor <molitdj97@gmail.com>
Requires-Python: >=3.10
Requires-Dist: numpy>=1.24.2
Requires-Dist: pandas>=2.0.0
Requires-Dist: plotnine>=0.12.0
Requires-Dist: tqdm>=4.50.0
